sofort/__init__.py
sofort/_version.py
sofort/client.py
sofort/exceptions.py
sofort/internals.py
sofort/model.py
sofort/xml.py
sofort-0.4.3.dist-info/DESCRIPTION.rst
sofort-0.4.3.dist-info/METADATA
sofort-0.4.3.dist-info/RECORD
sofort-0.4.3.dist-info/WHEEL
sofort-0.4.3.dist-info/metadata.json
sofort-0.4.3.dist-info/top_level.txt
