Metadata-Version: 2.0
Name: sofort
Version: 0.4.3
Summary: Sofort API
Home-page: https://github.com/spreecode/python-sofort
Author: Leonid Suprun
Author-email: mr.slay@gmail.com
License: MIT
Keywords: sofort
Platform: UNKNOWN
Classifier: Development Status :: 3 - Alpha
Classifier: Intended Audience :: Developers
Classifier: Topic :: Office/Business
Classifier: License :: OSI Approved :: MIT License
Classifier: Programming Language :: Python :: 2
Classifier: Programming Language :: Python :: 2.7
Requires-Dist: iso8601 (<1.0,>=0.1)
Requires-Dist: lxml (<4.0,>=3.5)
Requires-Dist: requests (>=2.9,<3.0)
Requires-Dist: schematics (<2.0,>=1.1)
Requires-Dist: xmltodict (>=0.9,<1.0)
Provides-Extra: test
Requires-Dist: coverage; extra == 'test'
Requires-Dist: mock; extra == 'test'
